baki/__init__.py
baki/app.py
baki/cli.py
baki/config.py
baki/interfaces.py
baki/logger.py
baki/restic_backend.py
baki-0.0.0.dist-info/METADATA
baki-0.0.0.dist-info/WHEEL
baki-0.0.0.dist-info/entry_points.txt
baki-0.0.0.dist-info/top_level.txt
baki-0.0.0.dist-info/RECORD
