Metadata-Version: 2.1
Name: baki
Version: 0.0.0
Summary: Backup wrapper for restic
Author-email: Kanelis Elias <e.kanelis@voidbuffer.com>
Maintainer-email: Kanelis Elias <e.kanelis@voidbuffer.com>
Project-URL: Homepage, https://pypi.org/project/baki/
Keywords: backup
Classifier: Development Status :: 3 - Alpha
Classifier: Programming Language :: Python :: 3
Classifier: Programming Language :: Python :: 3.10
Requires-Python: >3.10
Requires-Dist: xdg-base-dirs ==6.0.1
